README.rst
setup.cfg
setup.py
XtraDataManager/FeaturesExploitation.py
XtraDataManager/FeaturesExtraction.py
XtraDataManager/__init__.py
XtraDataManager.egg-info/PKG-INFO
XtraDataManager.egg-info/SOURCES.txt
XtraDataManager.egg-info/dependency_links.txt
XtraDataManager.egg-info/requires.txt
XtraDataManager.egg-info/top_level.txt