Metadata-Version: 1.1
Name: XtraDataManager
Version: 1.8
Summary: Kilosort/phy generated extracellular data managment, including supervised and unsupervised classification of units, in order to sort them by cell type.
Home-page: https://github.com/MS047/XtraDataManager
Author: Maxime Beau
Author-email: m.beau047@gmail.com
License: UNKNOWN
Download-URL: https://github.com/MS047/XtraDataManager/archive/1.8.tar.gz
Keywords: XtraDataManager,Phy,Classifier,sklearn,Extracellular,Spike Sorting,units,cell type
Platform: UNKNOWN
Classifier: Development Status :: 3 - Alpha
Classifier: Intended Audience :: Science/Research
Classifier: License :: OSI Approved :: MIT License
Classifier: Programming Language :: Python :: 3.5
Classifier: Environment :: Console
Classifier: Natural Language :: English
